{"name":"","id":"utest;","testSteps":[{"number":1,"description":"Given than Fabian wants be part of UTest","duration":30386,"startTime":"2022-11-16T16:24:08.893-05:00[America/Bogota]","screenshots":[{"screenshot":"13b97807b6ed4aaa2fd38785910e6fb086ed3d6130fde357f825530d3e1a9207.png","timeStamp":1668633879279}],"result":"SUCCESS","precondition":false,"level":0,"lineNumber":0,"children":[{"number":2,"description":"Fabian open up","duration":25020,"startTime":"2022-11-16T16:24:10.601-05:00[America/Bogota]","screenshots":[{"screenshot":"fe88801d59ac02c6d52aab2c66a2f0e7a78195ac84a233ea0865b324dfbde20d.png","timeStamp":1668633875621}],"result":"SUCCESS","precondition":false,"level":1,"lineNumber":0,"children":[{"number":3,"description":"Fabian opens the U test page","duration":24210,"startTime":"2022-11-16T16:24:10.651-05:00[America/Bogota]","screenshots":[{"screenshot":"fe88801d59ac02c6d52aab2c66a2f0e7a78195ac84a233ea0865b324dfbde20d.png","timeStamp":1668633874851}],"result":"SUCCESS","precondition":false,"level":2,"lineNumber":0}]},{"number":4,"description":"Fabian sign up","duration":3164,"startTime":"2022-11-16T16:24:35.642-05:00[America/Bogota]","screenshots":[{"screenshot":"60a6ef8fe20a8eae840a75b3fdfde1b19e09eee65b238f57f216520da0dec848.png","timeStamp":1668633878805}],"result":"SUCCESS","precondition":false,"level":1,"lineNumber":0,"children":[{"number":5,"description":"Fabian clicks on Button that shows the form of signup","duration":2412,"startTime":"2022-11-16T16:24:35.744-05:00[America/Bogota]","screenshots":[{"screenshot":"6f2cd381538978c8b98c6d09defc99365aff42f346f66f6cceef59210847bf79.png","timeStamp":1668633878141}],"result":"SUCCESS","precondition":false,"level":2,"lineNumber":0}]}]},{"number":6,"description":"When he registers all his personal datas at UTest","duration":82786,"startTime":"2022-11-16T16:24:39.299-05:00[America/Bogota]","screenshots":[{"screenshot":"9f67b2dfc28dbf2bd3d1d4ecf99d0852691fa3e0777a05448d033744835a90e4.png","timeStamp":1668633962084}],"result":"SUCCESS","precondition":false,"level":0,"lineNumber":0,"children":[{"number":7,"description":"Fabian first part","duration":24565,"startTime":"2022-11-16T16:24:39.567-05:00[America/Bogota]","screenshots":[{"screenshot":"58450426c9147c7f7f4615571e4c8a304aebd0accdf594ceb0fa66d5cf82f80b.png","timeStamp":1668633904131}],"result":"SUCCESS","precondition":false,"level":1,"lineNumber":0,"children":[{"number":8,"description":"Fabian enters \u0027FabianF\u0027 into input box for first name","duration":4965,"startTime":"2022-11-16T16:24:40.961-05:00[America/Bogota]","screenshots":[{"screenshot":"6a84e903afade9f7a51f81212ecf5fd45716c8d73c591db8695a11643b1a1ff2.png","timeStamp":1668633885916}],"result":"SUCCESS","precondition":false,"level":2,"lineNumber":0},{"number":9,"description":"Fabian enters \u0027VEGAS\u0027 into input box for last name","duration":2567,"startTime":"2022-11-16T16:24:46.003-05:00[America/Bogota]","screenshots":[{"screenshot":"7980c053a1d1d11da983bfdd1801554202c8e04af32db6bf31c71cbf62ed0851.png","timeStamp":1668633888563}],"result":"SUCCESS","precondition":false,"level":2,"lineNumber":0},{"number":10,"description":"Fabian enters \u0027FabianFfVeg@gmail.com\u0027 into input box for email","duration":2162,"startTime":"2022-11-16T16:24:48.610-05:00[America/Bogota]","screenshots":[{"screenshot":"6090ed7cfeedf838c514c1051ad372e5d633177d722614a93f307fd8bb5b5a98.png","timeStamp":1668633890764}],"result":"SUCCESS","precondition":false,"level":2,"lineNumber":0},{"number":11,"description":"Fabian enters \u0027May\u0027 into month select","duration":1204,"startTime":"2022-11-16T16:24:50.815-05:00[America/Bogota]","screenshots":[{"screenshot":"bf62650034ac09df3bf427fceaccc44ffc8fecad8b622258821d52dfb5b88c9e.png","timeStamp":1668633891995}],"result":"SUCCESS","precondition":false,"level":2,"lineNumber":0},{"number":12,"description":"Fabian enters \u002713\u0027 into day select","duration":1409,"startTime":"2022-11-16T16:24:52.069-05:00[America/Bogota]","screenshots":[{"screenshot":"cd9891e6b05a9f30a35d074770bc65d153355dd92fea355af154f63804c5267e.png","timeStamp":1668633893460}],"result":"SUCCESS","precondition":false,"level":2,"lineNumber":0},{"number":13,"description":"Fabian enters \u00271999\u0027 into year select","duration":1284,"startTime":"2022-11-16T16:24:53.529-05:00[America/Bogota]","screenshots":[{"screenshot":"50e0cf9b6c29b1e7e4514ec1325965390261614b57d77c4f8ba7bf81fbe2e257.png","timeStamp":1668633894812}],"result":"SUCCESS","precondition":false,"level":2,"lineNumber":0},{"number":14,"description":"Fabian clicks on button next: location","duration":7402,"startTime":"2022-11-16T16:24:54.850-05:00[America/Bogota]","screenshots":[{"screenshot":"cca3374ff8670c6872adee4e5c48fa54c96818916999cbad39f43c433f7bd462.png","timeStamp":1668633902231}],"result":"SUCCESS","precondition":false,"level":2,"lineNumber":0}]},{"number":15,"description":"Fabian second part","duration":27635,"startTime":"2022-11-16T16:25:04.195-05:00[America/Bogota]","screenshots":[{"screenshot":"1754b524f73605b8d21ebd1873057558361a38d50b9542536f6b5395abffe77f.png","timeStamp":1668633931830}],"result":"SUCCESS","precondition":false,"level":1,"lineNumber":0,"children":[{"number":16,"description":"Fabian enters \u0027Bogotá\u0027 into text field city","duration":10881,"startTime":"2022-11-16T16:25:04.696-05:00[America/Bogota]","screenshots":[{"screenshot":"e335f18cfbe0138c386a4f6e32dce60e9a30314efde4775f074e3529806e1f4e.png","timeStamp":1668633915561}],"result":"SUCCESS","precondition":false,"level":2,"lineNumber":0},{"number":17,"description":"Fabian types \u0027ARROW_DOWN\u0027 in text field city","duration":2587,"startTime":"2022-11-16T16:25:15.712-05:00[America/Bogota]","screenshots":[{"screenshot":"13146b20a474987b8be497e998d936474cf2907bc8edecd68ce376a0548d12b9.png","timeStamp":1668633918287}],"result":"SUCCESS","precondition":false,"level":2,"lineNumber":0},{"number":18,"description":"Fabian types \u0027ENTER\u0027 in text field city","duration":3655,"startTime":"2022-11-16T16:25:18.621-05:00[America/Bogota]","screenshots":[{"screenshot":"a4296bad0b51f64b25b5cc1c7433c8c41fe8de2d64cdd1da166c27c0d62dcb44.png","timeStamp":1668633922259}],"result":"SUCCESS","precondition":false,"level":2,"lineNumber":0},{"number":19,"description":"Fabian enters \u0027111166\u0027 into text field postal code","duration":3188,"startTime":"2022-11-16T16:25:22.516-05:00[America/Bogota]","screenshots":[{"screenshot":"4e6854a46eacf0273a306abde716235f1c76f3f8c81c7ad0c24a7e4bd1b6d315.png","timeStamp":1668633925691}],"result":"SUCCESS","precondition":false,"level":2,"lineNumber":0},{"number":20,"description":"Fabian clicks on button next device","duration":5536,"startTime":"2022-11-16T16:25:25.812-05:00[America/Bogota]","screenshots":[{"screenshot":"1754b524f73605b8d21ebd1873057558361a38d50b9542536f6b5395abffe77f.png","timeStamp":1668633931342}],"result":"SUCCESS","precondition":false,"level":2,"lineNumber":0}]},{"number":21,"description":"Fabian third part","duration":20786,"startTime":"2022-11-16T16:25:31.869-05:00[America/Bogota]","screenshots":[{"screenshot":"cfef5ea5743cd46f083bafc8a4cdb5c903a4316d0a04995ebb56bc4b5f03f8ac.png","timeStamp":1668633952655}],"result":"SUCCESS","precondition":false,"level":1,"lineNumber":0,"children":[{"number":22,"description":"Fabian clicks on select one of computer","duration":1897,"startTime":"2022-11-16T16:25:32.169-05:00[America/Bogota]","screenshots":[{"screenshot":"45440288baf5ed53044e3b8cb2b3082dae7d51a52daed45016a28baa3b2ff030.png","timeStamp":1668633934066}],"result":"SUCCESS","precondition":false,"level":2,"lineNumber":0},{"number":23,"description":"Fabian clicks on select one of so computer","duration":1651,"startTime":"2022-11-16T16:25:34.070-05:00[America/Bogota]","screenshots":[{"screenshot":"4975cef419f91da20dce372870a32699d0cda8b2a9ad1efa95e9d33c700f3996.png","timeStamp":1668633935714}],"result":"SUCCESS","precondition":false,"level":2,"lineNumber":0},{"number":24,"description":"Fabian clicks on select list version","duration":2091,"startTime":"2022-11-16T16:25:35.777-05:00[America/Bogota]","screenshots":[{"screenshot":"4846dfe3a531dd8b30daa68de73b0634dcda7c39555a7293b6f4c74738e339ee.png","timeStamp":1668633937862}],"result":"SUCCESS","precondition":false,"level":2,"lineNumber":0},{"number":25,"description":"Fabian clicks on select version","duration":1604,"startTime":"2022-11-16T16:25:37.938-05:00[America/Bogota]","screenshots":[{"screenshot":"4dde685066a908520a0596eefacbd51ae013a3ba546d5225ab11465b54b0f0a1.png","timeStamp":1668633939532}],"result":"SUCCESS","precondition":false,"level":2,"lineNumber":0},{"number":26,"description":"Fabian clicks on select one languaje","duration":3340,"startTime":"2022-11-16T16:25:39.682-05:00[America/Bogota]","screenshots":[{"screenshot":"b3638d5f2c2784bdf7bce83b437282ef4565dd3c551a6dc970977ed5bb1ed2c5.png","timeStamp":1668633943003}],"result":"SUCCESS","precondition":false,"level":2,"lineNumber":0},{"number":27,"description":"Fabian clicks on select one language","duration":2491,"startTime":"2022-11-16T16:25:43.154-05:00[America/Bogota]","screenshots":[{"screenshot":"e252cadb6709d282e93d1fb26e1c1594647a3c7e546b3ac9c7115214d32618b5.png","timeStamp":1668633945643}],"result":"SUCCESS","precondition":false,"level":2,"lineNumber":0},{"number":28,"description":"Fabian clicks on button next step","duration":4792,"startTime":"2022-11-16T16:25:45.961-05:00[America/Bogota]","screenshots":[{"screenshot":"124614fe9e20db060d989bea20ffa5d23cf361c9bdcd55439e37cb15ce1ea258.png","timeStamp":1668633950738}],"result":"SUCCESS","precondition":false,"level":2,"lineNumber":0}]},{"number":29,"description":"Fabian final part","duration":8654,"startTime":"2022-11-16T16:25:52.721-05:00[America/Bogota]","screenshots":[{"screenshot":"e89a4ce7c10b253dcdc1c305bafeedf7841a0a1a272766a620f5106b0599a582.png","timeStamp":1668633961375}],"result":"SUCCESS","precondition":false,"level":1,"lineNumber":0,"children":[{"number":30,"description":"Fabian enters \u0027Fabian987654321@\u0027 into box password","duration":2681,"startTime":"2022-11-16T16:25:52.954-05:00[America/Bogota]","screenshots":[{"screenshot":"987ca0801be59cda3f9acb212aff65e47f89bdd3a87cf7cffd2907e5b121f9e1.png","timeStamp":1668633955627}],"result":"SUCCESS","precondition":false,"level":2,"lineNumber":0},{"number":31,"description":"Fabian enters \u0027Fabian987654321@\u0027 into box confirm password","duration":2120,"startTime":"2022-11-16T16:25:55.707-05:00[America/Bogota]","screenshots":[{"screenshot":"5f8171283fd62066d5fe78d57752ca706e43bd277cc3c13e60a354f59cc395a6.png","timeStamp":1668633957827}],"result":"SUCCESS","precondition":false,"level":2,"lineNumber":0},{"number":32,"description":"Fabian clicks on check one","duration":1109,"startTime":"2022-11-16T16:25:57.830-05:00[America/Bogota]","screenshots":[{"screenshot":"b8c8d6b561a7c8558b0fac01de073da931528ed761c1d7a984fe4d20128bee07.png","timeStamp":1668633958939}],"result":"SUCCESS","precondition":false,"level":2,"lineNumber":0},{"number":33,"description":"Fabian clicks on check two","duration":996,"startTime":"2022-11-16T16:25:58.943-05:00[America/Bogota]","screenshots":[{"screenshot":"95ad7cd10f2979cc2ad05de459b0767f992414df859981bad3cf80393377d5e4.png","timeStamp":1668633959939}],"result":"SUCCESS","precondition":false,"level":2,"lineNumber":0},{"number":34,"description":"Fabian clicks on button of finish form","duration":1408,"startTime":"2022-11-16T16:25:59.942-05:00[America/Bogota]","screenshots":[{"screenshot":"e89a4ce7c10b253dcdc1c305bafeedf7841a0a1a272766a620f5106b0599a582.png","timeStamp":1668633961350}],"result":"SUCCESS","precondition":false,"level":2,"lineNumber":0}]}]},{"number":35,"description":"Then he registered and he sees Welcome to the world\u0027s largest community of freelance software testers!","duration":5288,"startTime":"2022-11-16T16:26:02.175-05:00[America/Bogota]","screenshots":[{"screenshot":"0dcb106fa6f00c761ceb8b8d7cd48ec29f06edd1b924e29ac2e8dda4c619cdd9.png","timeStamp":1668633967458}],"result":"SUCCESS","precondition":false,"level":0,"lineNumber":0,"children":[{"number":36,"description":"Then answer","duration":2557,"startTime":"2022-11-16T16:26:03.792-05:00[America/Bogota]","screenshots":[{"screenshot":"0dcb106fa6f00c761ceb8b8d7cd48ec29f06edd1b924e29ac2e8dda4c619cdd9.png","timeStamp":1668633966342}],"result":"SUCCESS","precondition":false,"level":1,"lineNumber":0}]}],"userStory":{"id":"utest","storyName":"UTest","path":"src/test/resources/features/uTest.feature","narrative":"  As a user, I have to complete the form of sign up at UTest for that I be part of UTesst page","type":"feature"},"featureTag":{"name":"Features/UTest","type":"feature","displayName":"Features/UTest"},"title":"","tags":[{"name":"UTest","type":"feature","displayName":"UTest"},{"name":"","type":"Scenario1","displayName":""},{"name":"stories","type":"tag","displayName":"stories"}],"startTime":"2022-11-16T16:24:08.591-05:00[America/Bogota]","duration":118922,"projectKey":"","sessionId":"b90e2870718ea787011c737bd41f19d4","driver":"chrome:fabian","isManualTestingUpToDate":false,"manual":false,"testSource":"Cucumber","actors":[{"name":"Fabian","can":["browse the web"]}],"result":"SUCCESS"}